marisco/__init__.py
marisco/_modidx.py
marisco/callbacks.py
marisco/configs.py
marisco/decoders.py
marisco/encoders.py
marisco/inout.py
marisco/metadata.py
marisco/netcdf2csv.py
marisco/utils.py
marisco/cli/__init__.py
marisco/cli/db_to_nc.py
marisco/cli/init.py
marisco/cli/nc_to_csv.py
marisco/cli/to_nc.py
marisco/handlers/__init__.py
marisco/handlers/geotraces.py
marisco/handlers/helcom.py
marisco/handlers/maris_legacy.py
marisco/handlers/ospar.py
marisco/handlers/tepco.py
marisco-1.0.4.dist-info/LICENSE
marisco-1.0.4.dist-info/METADATA
marisco-1.0.4.dist-info/WHEEL
marisco-1.0.4.dist-info/entry_points.txt
marisco-1.0.4.dist-info/top_level.txt
marisco-1.0.4.dist-info/RECORD
