Metadata-Version: 2.2
Name: marisco
Version: 1.0.4
Summary: MARIS companion package and tutorials
Home-page: https://github.com/franckalbinet/marisco
Author: Franck Albinet, Niall Murphy
Author-email: franckalbinet@gmail.com
License: Apache Software License 2.0
Keywords: nbdev jupyter notebook python netcdf marine radioactivity data
Classifier: Development Status :: 4 - Beta
Classifier: Intended Audience :: Developers
Classifier: Natural Language :: English
Classifier: Programming Language :: Python :: 3.7
Classifier: Programming Language :: Python :: 3.8
Classifier: Programming Language :: Python :: 3.9
Classifier: Programming Language :: Python :: 3.10
Classifier: Programming Language :: Python :: 3.11
Classifier: Programming Language :: Python :: 3.12
Classifier: License :: OSI Approved :: Apache Software License
Requires-Python: >=3.7
License-File: LICENSE
Requires-Dist: pandas
Requires-Dist: openpyxl
Requires-Dist: fastcore
Requires-Dist: rich
Requires-Dist: tqdm
Requires-Dist: netcdf4
Requires-Dist: tomli
Requires-Dist: tomli-w
Requires-Dist: shapely
Requires-Dist: pyzotero
Requires-Dist: jellyfish
Requires-Dist: requests
Requires-Dist: pyarrow
Requires-Dist: gevent>=22.10.2
Provides-Extra: dev
Requires-Dist: nbdev; extra == "dev"
Requires-Dist: ipykernel; extra == "dev"
Requires-Dist: twine; extra == "dev"
Dynamic: author
Dynamic: author-email
Dynamic: classifier
Dynamic: description
Dynamic: description-content-type
Dynamic: home-page
Dynamic: keywords
Dynamic: license
Dynamic: provides-extra
Dynamic: requires-dist
Dynamic: requires-python
Dynamic: summary
